LICENSE
MANIFEST.in
README.md
setup.py
easyjudge/__init__.py
easyjudge/app.py
easyjudge/config.json
easyjudge/participants.json
easyjudge.egg-info/PKG-INFO
easyjudge.egg-info/SOURCES.txt
easyjudge.egg-info/dependency_links.txt
easyjudge.egg-info/entry_points.txt
easyjudge.egg-info/requires.txt
easyjudge.egg-info/top_level.txt
easyjudge/download/.keep
easyjudge/download/__init__.py
easyjudge/download/inference_template.py
easyjudge/download/数据集A.csv
easyjudge/download/数据集B.csv
easyjudge/download/grape_orange/1.可视化数据.py
easyjudge/download/grape_orange/2.训练.py
easyjudge/download/grape_orange/Oranges_Grapefruit.csv
easyjudge/download/grape_orange/Oranges_Grapefruit_10000.csv
easyjudge/templates/__init__.py
easyjudge/templates/admin.html
easyjudge/templates/index.html